jpl/labcas/utils/VERSION.txt
jpl/labcas/utils/__init__.py
jpl/labcas/utils/annual_report.py
jpl/labcas/utils/api_patching.py
jpl/labcas/utils/argparse.py
jpl/labcas/utils/assign_uuids.py
jpl/labcas/utils/backups.py
jpl/labcas/utils/bbd_dcis_population.py
jpl/labcas/utils/bbd_dcis_restructuring.py
jpl/labcas/utils/collection_deletion.py
jpl/labcas/utils/common_prefixes.py
jpl/labcas/utils/const.py
jpl/labcas/utils/date_report.py
jpl/labcas/utils/dcm_header_usage.py
jpl/labcas/utils/dcm_splitter.py
jpl/labcas/utils/delete_datasets.py
jpl/labcas/utils/delete_field.py
jpl/labcas/utils/dmcc_api.py
jpl/labcas/utils/event_id_repair.py
jpl/labcas/utils/field_usage_report.py
jpl/labcas/utils/file_size.py
jpl/labcas/utils/header_mangling.py
jpl/labcas/utils/mass_spec_fixer.py
jpl/labcas/utils/missing_bbd_dcis_images.py
jpl/labcas/utils/missing_event_ids.py
jpl/labcas/utils/patient_id_fixer.py
jpl/labcas/utils/principal_fixer.py
jpl/labcas/utils/rdf.py
jpl/labcas/utils/replace_field.py
jpl/labcas/utils/replace_fields.py
jpl/labcas/utils/report_fields.py
jpl/labcas/utils/reports.py
jpl/labcas/utils/s3_report.py
jpl/labcas/utils/solr.py
jpl/labcas/utils/split_brsi.py
jpl/labcas/utils/sub_field.py
jpl_labcas_utils-0.0.2.dist-info/METADATA
jpl_labcas_utils-0.0.2.dist-info/WHEEL
jpl_labcas_utils-0.0.2.dist-info/entry_points.txt
jpl_labcas_utils-0.0.2.dist-info/licenses/LICENSE.md
jpl_labcas_utils-0.0.2.dist-info/licenses/NOTICE.txt
jpl_labcas_utils-0.0.2.dist-info/RECORD
