Metadata-Version: 2.4
Name: jpl.labcas.utils
Version: 0.0.2
Summary: Utilities for the Laboratory Catalog and Archive Service of the Early Detection Research Network
Project-URL: Homepage, https://github.com/EDRN/jpl.labcas.utils
Project-URL: Issues, https://github.com/EDRN/jpl.labcas.utils/issues
Author-email: Sean Kelly <kelly@seankelly.biz>
License: Apache License
License-File: LICENSE.md
License-File: NOTICE.txt
Keywords: archive,cancer,catalog,data,edrn,jpl,labcas,nasa,nci,nih
Classifier: Development Status :: 2 - Pre-Alpha
Classifier: Intended Audience :: Healthcare Industry
Classifier: Intended Audience :: Science/Research
Classifier: License :: OSI Approved :: Apache Software License
Classifier: Natural Language :: English
Classifier: Operating System :: OS Independent
Classifier: Programming Language :: Python :: 3
Requires-Python: >=3.12
Requires-Dist: boto3~=1.36.5
Requires-Dist: gdown~=5.2.0
Requires-Dist: humanize~=4.12.3
Requires-Dist: numpy~=2.3.0
Requires-Dist: pandas~=2.3.0
Requires-Dist: pydicom~=3.0.1
Requires-Dist: pysolr~=3.10.0
Requires-Dist: rdflib~=5.0.0
Requires-Dist: requests~=2.32.3
